{
    "waifu": {
        "console_open_msg": ["哈哈，你打开了控制台，是想要看看我的秘密吗？"],
        "copy_message": ["你都复制了些什么呀，转载要记得加上出处哦"],
        "screenshot_message": ["照好了嘛，是不是很可爱呢？"],
        "hidden_message": ["舰长补给全保底，舰长副本零掉落"],
        "load_rand_textures": ["我还没有其他衣服呢", "我的新衣服好看嘛"],
        "hour_tips": {
            "t5-7": ["早上好！一日之计在于晨，美好的一天就要开始了"],
            "t7-11": ["上午好！工作顺利嘛，不要久坐，多起来走动走动哦！"],
            "t11-14": ["中午了，工作了一个上午，现在是午餐时间！"],
            "t14-17": ["午后很容易犯困呢，今天的运动目标完成了吗？"],
            "t17-19": ["傍晚了！窗外夕阳的景色很美丽呢，最美不过夕阳红~"],
            "t19-21": ["晚上好，今天过得怎么样？"],
            "t21-23": ["已经这么晚了呀，早点休息吧，晚安~"],
            "t23-5": ["你是夜猫子呀？这么晚还不睡觉，明天起的来嘛"],
            "default": ["嗨~ 快来逗我玩吧！"]
        },
        "referrer_message": {
            "localhost": ["正在阅读<span style=\"color:DarkBlue;\">『", "』</span>", " - "],
            "baidu": ["Hello! 来自 百度搜索 的朋友<br>你是搜索 <span style=\"color:DarkBlue;\">", "</span> 找到的我吗？"],
            "so": ["Hello! 来自 360搜索 的朋友<br>你是搜索 <span style=\"color:DarkBlue;\">", "</span> 找到的我吗？"],
            "google": ["Hello! 来自 谷歌搜索 的朋友<br>欢迎阅读<span style=\"color:DarkBlue;\">『", "』</span>", " - "],
            "default": ["Hello! 来自 <span style=\"color:DarkBlue;\">", "</span> 的朋友"],
            "none": ["正在阅读<span style=\"color:DarkBlue;\">『", "』</span>", " - "]
        },
        "referrer_hostname": {
            "note6.konata.tech": ["果然还是离不开我吧^_^"],
            "note.konata.tech": ["果然还是离不开我吧^_^"]
        },
        "model_message": {},
        "hitokoto_api_message": {
            "lwl12.com": ["这句一言来自 <span style=\"color:DarkBlue;\">『{source}』</span>", "，是 <span style=\"color:DarkBlue;\">{creator}</span> 投稿的", "。"],
            "fghrsh.net": ["这句一言出处是 <span style=\"color:DarkBlue;\">『{source}』</span>，是 <span style=\"color:DarkBlue;\">FGHRSH</span> 在 {date} 收藏的！"],
            "jinrishici.com": ["这句诗词出自 <span style=\"color:DarkBlue;\">《{title}》</span>，是 {dynasty}诗人 {author} 创作的！"],
            "hitokoto.cn": [
                "这句一言来自 <span style=\"color:DarkBlue;\">『{source}』</span>，是 <span style=\"color:DarkBlue;\">{creator}</span> 在 hitokoto.cn 投稿的。"
            ]
        }
    },
    "mouseover": [
        {
            "selector": ".container a[href^=\"http\"]",
            "text": ["要看看 <span style=\"color:DarkBlue;\">{text}</span> 么？"]
        }, {
            "selector": ".waifu-tool>.icon-home",
            "text": ["点击这里前往首页哦~"]
        }, {
            "selector": "#floating-toc-btn",
            "text": ["翻页比较麻烦吗，点击可以显示这篇文章的目录呢"]
        }, {
            "selector": ".mute",
            "text": ["点这里可以静音哦"]
        }, {
            "selector": "a[href^=\"/\"]>.fa-angle-left",
            "text": ["去上一页看看吧"]
        }, {
            "selector": "a[href^=\"/page/\"]>.fa-angle-right",
            "text": ["去下一页看看吧"]
        }, {
            "selector": "#comment",
            "text": ["在这里可以调整<span style=\"color:DarkBlue;\">音量</span>呢"]
        }, {
            "selector": "#comment",
            "text": ["<span style=\"color:DarkBlue;\">播放列表</span>里都有什么呢"]
        }, {
            "selector": ".protyle-gutters",
            "text": ["点这个可以呼出块设置菜单哦"]
        }, {
            "selector": ".protyle-action",
            "text": ["点这个可以进入聚焦模式哦"]
        }, {
            "selector": ".protyle-scroll",
            "text": ["东西太多了，要滚动页面吗"]
        }, {
            "selector": ".protyle-scroll__up",
            "text": ["跳转到开头看看吧"]
        }, {
            "selector": ".protyle-scroll__down",
            "text": ["跳转到末尾看看吧"]
        }, {
            "selector": ".protyle-util",
            "text": ["要备注些什么呢"]
        }, {
            "selector": "#live2d2,#live2d4",
            "text": [
                "派蒙今年的生日愿望，就是希望能够一直陪在旅行者身边！",
                "呜…我理解。要是有一天我和（玩家名）分开了，我也一定习惯不了…可能还会对着空气自言自语…", 
                "唉，明明都一起来的，现在又只剩下我们两个…不过这么一想，我们两个单独相处的时间也已经有好多好多了呢。", 
                "唔、那个…没有别的意思，就是、就是想稍微问一下…和我在一起不会很无聊吧？", 
                "解锁全部奇遇了！不过，我才是你旅行中最大最特殊的奇遇吧！",
                "就算你现在已经契约了影狼丸，你也不能忘记派蒙是你最最最好的伙伴哦！", 
                "我的愿望就是实现你的愿望哦。", 
                "没错！你的幸福就是派蒙的幸福呀！所以反过来说，派蒙幸福，你也幸福。", 
                "我们是不会分开的，对吗？我们还要一起走很远很远的路，度过好久好久的时光。"
            ]
        }
    ],
    "click": [
        {
            "selector": "#live2d2,#live2d4",
            "text": [
                "派蒙今年的生日愿望，就是希望能够一直陪在旅行者身边！",
                "呜…我理解。要是有一天我和你分开了，我也一定习惯不了…可能还会对着空气自言自语…", 
                "唉，明明都一起来的，现在又只剩下我们两个…不过这么一想，我们两个单独相处的时间也已经有好多好多了呢。", 
                "唔、那个…没有别的意思，就是、就是想稍微问一下…和我在一起不会很无聊吧？", 
                "解锁全部奇遇了！不过，我才是你旅行中最大最特殊的奇遇吧！",
                "就算你现在已经契约了影狼丸，你也不能忘记派蒙是你最最最好的伙伴哦！", 
                "我的愿望就是实现你的愿望哦。", 
                "没错！你的幸福就是派蒙的幸福呀！所以反过来说，派蒙幸福，你也幸福。", 
                "我们是不会分开的，对吗？我们还要一起走很远很远的路，度过好久好久的时光。"
            ]
        }
    ],
    "seasons": [
        {
            "date": "01/01",
            "text": ["<span style=\"color:DarkBlue;\">元旦</span>了呢，新的一年又开始了，今年是{year}年~"]
        }, {
            "date": "02/14",
            "text": ["又是一年<span style=\"color:DarkBlue;\">情人节</span>，{year}年找到对象了嘛~"]
        }, {
            "date": "03/08",
            "text": ["今天是<span style=\"color:DarkBlue;\">妇女节</span>！"]
        }, {
            "date": "03/12",
            "text": ["今天是<span style=\"color:DarkBlue;\">植树节</span>，要保护环境呀"]
        }, {
            "date": "04/01",
            "text": ["悄悄告诉你一个秘密~<span style=\"background-color:#34495e;\">今天是愚人节，不要被骗了哦~</span>"]
        }, {
            "date": "05/01",
            "text": ["今天是<span style=\"color:DarkBlue;\">五一劳动节</span>，计划好假期去哪里了吗~"]
        }, {
            "date": "06/01",
            "text": ["<span style=\"color:DarkBlue;\">儿童节</span>了呢，快活的时光总是短暂，要是永远长不大该多好啊…"]
        }, {
            "date": "09/03",
            "text": ["<span style=\"color:DarkBlue;\">中国人民抗日战争胜利纪念日</span>，铭记历史、缅怀先烈、珍爱和平、开创未来。"]
        }, {
            "date": "09/10",
            "text": ["<span style=\"color:DarkBlue;\">教师节</span>，在学校要给老师问声好呀~"]
        }, {
            "date": "10/01",
            "text": ["<span style=\"color:DarkBlue;\">国庆节</span>，新中国已经成立71年了呢"]
        }, {
            "date": "11/05-11/12",
            "text": ["今年的<span style=\"color:DarkBlue;\">双十一</span>是和谁一起过的呢~"]
        }, {
            "date": "12/20-12/31",
            "text": ["这几天是<span style=\"color:DarkBlue;\">圣诞节</span>，主人肯定又去剁手买买买了~"]
        }
    ]
}